README.md
setup.cfg
setup.py
src/mimosa/__init__.py
src/mimosa/models/__init__.py
src/mimosa/models/_auto_db_schema.py
src/mimosa/models/base.py
src/mimosa_models.egg-info/PKG-INFO
src/mimosa_models.egg-info/SOURCES.txt
src/mimosa_models.egg-info/dependency_links.txt
src/mimosa_models.egg-info/requires.txt
src/mimosa_models.egg-info/top_level.txt
tests/test_models.py