Metadata-Version: 2.1
Name: mimosa-models
Version: 2.2.0
Summary: SQLAlchemy ORM models for the mimosa database
Home-page: https://gitlab.esrf.fr/ui/mimosa/mimosa-models
Author: ESRF
Author-email: daiquiri-feedback@esrf.fr
License: Apache License, Version 2.0
Keywords: mimosa,daiquiri,database,SQLAlchemy
Classifier: Development Status :: 5 - Production/Stable
Classifier: License :: OSI Approved :: Apache Software License
Classifier: Programming Language :: Python :: 3
Classifier: Programming Language :: Python :: 3.7
Classifier: Programming Language :: Python :: 3.8
Classifier: Programming Language :: Python :: 3.9
Classifier: Programming Language :: Python :: 3.10
Classifier: Operating System :: OS Independent
Classifier: Topic :: Software Development :: Libraries :: Python Modules
Requires-Python: >=3.7
Requires-Dist: mysql-connector-python
Requires-Dist: sqlalchemy
